main.py
lms_by_shahab-0.1.1.dist-info/METADATA
lms_by_shahab-0.1.1.dist-info/WHEEL
lms_by_shahab-0.1.1.dist-info/entry_points.txt
lms_by_shahab-0.1.1.dist-info/top_level.txt
lms_by_shahab-0.1.1.dist-info/RECORD
