Metadata-Version: 2.2
Name: lms-by-shahab
Version: 0.1.1
Summary: It Is A Real Library Management System using MySQL as a Database
Author-email: Shahabuddin <voyagersvrs135@gmail.com>
Requires-Python: >=3.12
Requires-Dist: inquirer>=3.4.0
Requires-Dist: mysql-connector-python>=9.2.0
Requires-Dist: python-dotenv>=1.0.1
